datavalidator/__init__.py
datavalidator/validator.py
LegacyDataValidator-0.1.2.dist-info/LICENSE
LegacyDataValidator-0.1.2.dist-info/METADATA
LegacyDataValidator-0.1.2.dist-info/WHEEL
LegacyDataValidator-0.1.2.dist-info/top_level.txt
LegacyDataValidator-0.1.2.dist-info/RECORD
