Metadata-Version: 2.1
Name: LegacyDataValidator
Version: 0.1.2
Summary: A simple data validation library
Home-page: https://github.com/S1lentAFK/data_validator
Author: o_frun
Classifier: Development Status :: 3 - Alpha
Classifier: Intended Audience :: Developers
Classifier: License :: OSI Approved :: MIT License
Classifier: Programming Language :: Python :: 3
Classifier: Programming Language :: Python :: 3.7
Classifier: Programming Language :: Python :: 3.8
Classifier: Programming Language :: Python :: 3.9
Requires-Python: >=3.7
License-File: LICENSE
